inaccel_vitis-0.2-py3.8-nspkg.pth
inaccel/vitis/__init__.py
inaccel/vitis/fintech/__init__.py
inaccel/vitis/fintech/xf_fintech_binomialtree.py
inaccel/vitis/fintech/xf_fintech_cf_black_scholes.py
inaccel/vitis/fintech/xf_fintech_mc_american.py
inaccel/vitis/fintech/xf_fintech_types.py
inaccel/vitis/vision/__init__.py
inaccel/vitis/vision/_vision_stereobm.py
inaccel/vitis/vision/_vision_stereobm_video.py
inaccel_vitis-0.2.dist-info/METADATA
inaccel_vitis-0.2.dist-info/WHEEL
inaccel_vitis-0.2.dist-info/namespace_packages.txt
inaccel_vitis-0.2.dist-info/top_level.txt
inaccel_vitis-0.2.dist-info/zip-safe
inaccel_vitis-0.2.dist-info/RECORD
